LICENSE
hamcws/__init__.py
hamcws/hamcws.py
hamwcs-0.0.3.dist-info/LICENSE
hamwcs-0.0.3.dist-info/METADATA
hamwcs-0.0.3.dist-info/WHEEL
hamwcs-0.0.3.dist-info/RECORD
