Metadata-Version: 2.1
Name: hamwcs
Version: 0.0.3
Summary: homeassistant friendly wrapper for J River MCWS
Home-page: http://github.com/3ll3d00d/hamcws
License: MIT
Author: 3ll3d00d
Author-email: mattkhan+hamcws@gmail.com
Requires-Python: >=3.11,<3.12
Classifier: License :: OSI Approved :: MIT License
Classifier: Programming Language :: Python :: 3
Classifier: Programming Language :: Python :: 3.11
Requires-Dist: aiohttp (>=3.9.1,<4.0.0)
Project-URL: Repository, http://github.com/3ll3d00d/hamcws
